{
  "updatedAt": "2026-07-22 05:00",
  "items": [
    {
      "symbol": "SPY",
      "label": "S&P 500",
      "price": 746.4239,
      "changePct": -0.25
    },
    {
      "symbol": "QQQ",
      "label": "Nasdaq 100",
      "price": 704.11,
      "changePct": -0.69
    },
    {
      "symbol": "DIA",
      "label": "Dow Jones",
      "price": 521.2,
      "changePct": -0.06
    },
    {
      "symbol": "AAPL",
      "label": "Apple",
      "price": 327.72,
      "changePct": -0.01
    },
    {
      "symbol": "MSFT",
      "label": "Microsoft",
      "price": 398.8825,
      "changePct": 0.28
    },
    {
      "symbol": "GOOGL",
      "label": "Alphabet",
      "price": 349.37,
      "changePct": 0.64
    },
    {
      "symbol": "AMZN",
      "label": "Amazon",
      "price": 247.7359,
      "changePct": 0.08
    },
    {
      "symbol": "NVDA",
      "label": "Nvidia",
      "price": 205.2,
      "changePct": -1.01
    },
    {
      "symbol": "META",
      "label": "Meta",
      "price": 643.78,
      "changePct": 0
    },
    {
      "symbol": "TSLA",
      "label": "Tesla",
      "price": 378.4,
      "changePct": -0.14
    },
    {
      "symbol": "SPCX",
      "label": "SpaceX",
      "price": 124.6,
      "changePct": 0.86
    },
    {
      "symbol": "ORCL",
      "label": "Oracle",
      "price": 126.25,
      "changePct": -0.63
    },
    {
      "symbol": "PLTR",
      "label": "Palantir",
      "price": 132.79,
      "changePct": 0.1
    },
    {
      "symbol": "IBM",
      "label": "IBM",
      "price": 211.9865,
      "changePct": 0.71
    },
    {
      "symbol": "MSTR",
      "label": "Strategy",
      "price": 100.77,
      "changePct": -1.16
    },
    {
      "symbol": "COIN",
      "label": "Coinbase",
      "price": 174.87,
      "changePct": -0.56
    },
    {
      "symbol": "CRCL",
      "label": "Circle",
      "price": 69.18,
      "changePct": -2.67
    },
    {
      "symbol": "HOOD",
      "label": "Robinhood",
      "price": 105.88,
      "changePct": -0.45
    }
  ]
}
